AUTHORS
LICENSE
MANIFEST.in
README.rst
Semantic.GS-LICENSE
setup.py
caktus_sphinx_theme.egg-info/PKG-INFO
caktus_sphinx_theme.egg-info/SOURCES.txt
caktus_sphinx_theme.egg-info/dependency_links.txt
caktus_sphinx_theme.egg-info/not-zip-safe
caktus_sphinx_theme.egg-info/requires.txt
caktus_sphinx_theme.egg-info/top_level.txt
caktus_theme/__init__.py
caktus_theme/theme/caktus/index-sidebar.html
caktus_theme/theme/caktus/layout.html
caktus_theme/theme/caktus/theme.conf
caktus_theme/theme/caktus/static/caktus-logo.png
caktus_theme/theme/caktus/static/caktus.css
caktus_theme/theme/caktus/static/caktus.less
caktus_theme/theme/caktus/static/favicon.png
caktus_theme/theme/caktus/static/grid.less