Metadata-Version: 1.0
Name: caktus-sphinx-theme
Version: 0.1.0
Summary: Custom Sphinx theme for projects written and maintained by Caktus Consulting Group.
Home-page: https://github.com/caktus/caktus-sphinx-theme/
Author: Caktus Consulting Group
Author-email: solutions@caktusgroup.com
License: BSD
Platform: UNKNOWN
Classifier: License :: OSI Approved :: BSD License
Classifier: Programming Language :: Python
Classifier: Programming Language :: Python :: 2.6
Classifier: Programming Language :: Python :: 2.7
Classifier: Development Status :: 4 - Beta
Classifier: Operating System :: OS Independent
